<?xml version = '1.0' encoding = 'UTF-8'?>
<Diagram class="oracle.dbtools.crest.swingui.relational.DPVRelational" name="Github" id="A9F101DC-9772-445B-0503-8F133FAADB06">
<createdBy>Lalos</createdBy>
<modifiedBy>Lalos</modifiedBy>
<createdTime>2024-02-19 22:59:07 UTC</createdTime>
<autoRoute>false</autoRoute>
<boxInbox>true</boxInbox>
<showLegend>false</showLegend>
<showLabels>false</showLabels>
<showRelAttributes>false</showRelAttributes>
<gridEnabled>false</gridEnabled>
<showGrid>false</showGrid>
<diagramColor>-1</diagramColor>
<display>false</display>
<notation>1</notation>
<objectViews>
<OView class="oracle.dbtools.crest.swingui.relational.TVTable" oid="00CC39FC-E9BA-6227-4493-E4B6386F3EEF" otype="Table" vid="F9FAB16C-E004-F710-A56A-16B4C1EA1F4A">
<hideElementsInCurrentOnly>false</hideElementsInCurrentOnly>
<bounds x="1969" y="303" width="227" height="96"/>
</OView>
<OView class="oracle.dbtools.crest.swingui.TVNote" oid="072BDB21-22F5-FA52-3F64-03497F96FED3" otype="Note" vid="A4835C15-6129-37B2-F3E1-0405074CE8FF">
<hideElementsInCurrentOnly>false</hideElementsInCurrentOnly>
<bounds x="673" y="1311" width="131" height="44"/>
<comment>OBS: Un equipo puede tener varios miembros</comment>
</OView>
<OView class="oracle.dbtools.crest.swingui.relational.TVTable" oid="078721A1-58A8-2D65-6A3A-7E6252826D75" otype="Table" vid="A434CD4D-D16D-93C9-9F74-BD060AEE9DA1">
<hideElementsInCurrentOnly>false</hideElementsInCurrentOnly>
<bounds x="1213" y="1089" width="266" height="195"/>
</OView>
<OView class="oracle.dbtools.crest.swingui.relational.TVTable" oid="14FEF448-CE53-72E3-3F59-FF5CEED7D372" otype="Table" vid="17D69F52-DC97-ED43-3D14-0DAC1F7EFA80">
<hideElementsInCurrentOnly>false</hideElementsInCurrentOnly>
<bounds x="605" y="172" width="254" height="150"/>
</OView>
<OView class="oracle.dbtools.crest.swingui.relational.TVTable" oid="17E64F32-3EC1-1C32-77BD-59BA03BE71E0" otype="Table" vid="D053F686-7233-6B6D-9028-7E800EDE3FC4">
<hideElementsInCurrentOnly>false</hideElementsInCurrentOnly>
<bounds x="622" y="1171" width="210" height="113"/>
</OView>
<OView class="oracle.dbtools.crest.swingui.relational.TVTable" oid="1D952C29-94D7-A28E-8318-6CD170F7A4BC" otype="Table" vid="23AD38DB-F80C-7E78-779B-00858097C394">
<hideElementsInCurrentOnly>false</hideElementsInCurrentOnly>
<bounds x="1697" y="719" width="232" height="118"/>
</OView>
<OView class="oracle.dbtools.crest.swingui.relational.TVTable" oid="3842C7DE-37FC-C241-7196-A0BAA6DC18AD" otype="Table" vid="DDF73358-AE62-C47E-6D35-7443944B37FC">
<hideElementsInCurrentOnly>false</hideElementsInCurrentOnly>
<bounds x="198" y="356" width="255" height="99"/>
</OView>
<OView class="oracle.dbtools.crest.swingui.TVNote" oid="407F6F15-521F-6DF0-725E-B81513B624A3" otype="Note" vid="F4A81E6C-F625-553E-BBF7-D45D55DC40BF">
<hideElementsInCurrentOnly>false</hideElementsInCurrentOnly>
<bounds x="507" y="603" width="105" height="58"/>
<comment>OBS: Un usuario puede hacer varios comentarios</comment>
</OView>
<OView class="oracle.dbtools.crest.swingui.relational.TVTable" oid="41379A4C-E08B-5B07-05D9-604FBF6E1724" otype="Table" vid="4A57AB56-8CB8-9FF1-B6F6-62930E10D589">
<hideElementsInCurrentOnly>false</hideElementsInCurrentOnly>
<bounds x="174" y="580" width="301" height="122"/>
</OView>
<OView class="oracle.dbtools.crest.swingui.TVNote" oid="56567A51-C4B7-1DB2-055D-60C0457810B2" otype="Note" vid="05F453AB-84A4-71A6-7F2F-6EBB70C9C897">
<hideElementsInCurrentOnly>false</hideElementsInCurrentOnly>
<bounds x="495" y="399" width="135" height="37"/>
<comment>OBS: Un usuario puede tener varios seguidores
</comment>
</OView>
<OView class="oracle.dbtools.crest.swingui.TVNote" oid="6672F771-752B-EC57-9826-BC17438FA139" otype="Note" vid="60081447-9D82-C288-D8F0-6B13795A97CE">
<hideElementsInCurrentOnly>false</hideElementsInCurrentOnly>
<bounds x="659" y="1088" width="137" height="40"/>
<comment>OBS: Una organizacion puede tener varios equipos

</comment>
</OView>
<OView class="oracle.dbtools.crest.swingui.TVNote" oid="6B100BFA-7F4D-C849-D9AB-B0A66A7D5F2B" otype="Note" vid="A7D54302-9E0F-B6AA-CDBD-A99F3D684C93">
<hideElementsInCurrentOnly>false</hideElementsInCurrentOnly>
<bounds x="692" y="399" width="101" height="50"/>
<comment>OBS: Un usuario puede tener varios proyectos</comment>
</OView>
<OView class="oracle.dbtools.crest.swingui.relational.TVTable" oid="72652D7F-1A6A-5000-2D87-6C5E0BE7823B" otype="Table" vid="9AE03005-8EDB-2D3D-98EF-90E44E8E8078">
<hideElementsInCurrentOnly>false</hideElementsInCurrentOnly>
<bounds x="1028" y="819" width="261" height="192"/>
</OView>
<OView class="oracle.dbtools.crest.swingui.TVNote" oid="79CC7CB0-B174-67D3-EE6B-EA57EAE1477B" otype="Note" vid="B7A350BA-A06D-4B7A-352A-FA9C83FDC057">
<hideElementsInCurrentOnly>false</hideElementsInCurrentOnly>
<bounds x="1156" y="712" width="123" height="74"/>
<comment>OBS: Varios colaboradores pueden trabajar en un repositorio
</comment>
</OView>
<OView class="oracle.dbtools.crest.swingui.relational.TVTable" oid="7BF65CEE-06D8-F147-A408-53877BFD1C27" otype="Table" vid="ECD4FF18-2A6E-48B2-4BC6-43E7E8F695A8">
<hideElementsInCurrentOnly>false</hideElementsInCurrentOnly>
<bounds x="622" y="1399" width="202" height="97"/>
</OView>
<OView class="oracle.dbtools.crest.swingui.relational.TVTable" oid="802222FD-7BE4-8A5E-0AC2-D2AE8947D3B1" otype="Table" vid="E61C62B3-ED4B-6957-8916-1B45C6FC082D">
<hideElementsInCurrentOnly>false</hideElementsInCurrentOnly>
<bounds x="636" y="503" width="288" height="192"/>
</OView>
<OView class="oracle.dbtools.crest.swingui.relational.TVTable" oid="861E815B-1D33-BE9E-1D89-662303288EFD" otype="Table" vid="D8C0244D-4372-576F-F2A5-13780CB6902D">
<hideElementsInCurrentOnly>false</hideElementsInCurrentOnly>
<bounds x="1442" y="232" width="241" height="107"/>
</OView>
<OView class="oracle.dbtools.crest.swingui.relational.TVTable" oid="88483D41-2875-45F1-827A-98F8FC652931" otype="Table" vid="6D7F1AC2-9EEC-AA46-0EAA-51EA37291CCA">
<hideElementsInCurrentOnly>false</hideElementsInCurrentOnly>
<bounds x="1156" y="486" width="322" height="197"/>
</OView>
<OView class="oracle.dbtools.crest.swingui.TVNote" oid="8EE4C60E-5EA7-E07B-3858-9E11A974648C" otype="Note" vid="4E42B9D4-947D-0431-3015-B6C96780AB5E">
<hideElementsInCurrentOnly>false</hideElementsInCurrentOnly>
<bounds x="964" y="553" width="166" height="67"/>
<comment>OBS: Un usuario puede tener varios repositorios, pero un repositorio puede tener varios usuarios.</comment>
</OView>
<OView class="oracle.dbtools.crest.swingui.relational.TVTable" oid="B5E8A1C5-AE73-D7FA-7873-9A727560CABC" otype="Table" vid="77A89C16-F31B-95D5-864E-A476AF0E1FC1">
<hideElementsInCurrentOnly>false</hideElementsInCurrentOnly>
<bounds x="1709" y="299" width="234" height="112"/>
</OView>
<OView class="oracle.dbtools.crest.swingui.relational.TVTable" oid="BF202CF1-85D8-DE82-7A42-F482DF350C6B" otype="Table" vid="E9319264-21B4-086C-C57D-8A3E04F07075">
<hideElementsInCurrentOnly>false</hideElementsInCurrentOnly>
<bounds x="1931" y="537" width="305" height="145"/>
</OView>
<OView class="oracle.dbtools.crest.swingui.relational.TVTable" oid="C633091B-2759-BFEF-4B57-23B4A5FB505E" otype="Table" vid="7F4C35F9-7094-B775-1E75-5C8B980D02D9">
<hideElementsInCurrentOnly>false</hideElementsInCurrentOnly>
<bounds x="1186" y="126" width="236" height="112"/>
</OView>
<OView class="oracle.dbtools.crest.swingui.relational.TVTable" oid="D607C967-EE4D-2728-E549-5D8FC05E2ECC" otype="Table" vid="10875E27-7942-D7FD-BC2D-8685C4EFB84E">
<hideElementsInCurrentOnly>false</hideElementsInCurrentOnly>
<bounds x="593" y="889" width="259" height="160"/>
</OView>
<OView class="oracle.dbtools.crest.swingui.relational.TVTable" oid="FB61A858-5D34-CDAA-EEB1-DEA78DF292B1" otype="Table" vid="E1EA7A8A-44C2-1398-DBC0-9FC899F25D67">
<hideElementsInCurrentOnly>false</hideElementsInCurrentOnly>
<bounds x="1387" y="778" width="234" height="133"/>
</OView>
<OView class="oracle.dbtools.crest.swingui.relational.TVTable" oid="FB8E507A-B926-916E-1BA4-872ACD52678D" otype="Table" vid="F90DCE8B-2C27-9257-F516-49C2F3EB688B">
<hideElementsInCurrentOnly>false</hideElementsInCurrentOnly>
<bounds x="921" y="270" width="237" height="150"/>
</OView>
</objectViews>
<connectors>
<Connector class="oracle.dbtools.crest.swingui.relational.TVFKRelation" oid="11693606-E8AE-5C60-7B28-0E82293BCC68" otype="FKIndexAssociation" vid_source="6D7F1AC2-9EEC-AA46-0EAA-51EA37291CCA" vid_target="23AD38DB-F80C-7E78-779B-00858097C394">
<hideElementsInCurrentOnly>false</hideElementsInCurrentOnly>
<backgroundColor>-16777216</backgroundColor>
<lineWidth>1</lineWidth>
<points>
<point x="1478" y="644"/>
<point x="1826" y="644"/>
<point x="1826" y="719"/>
</points>
</Connector>
<Connector class="oracle.dbtools.crest.swingui.relational.TVFKRelation" oid="1D8B312B-DFDF-7B42-7DE3-C61144CD4B5C" otype="FKIndexAssociation" vid_source="E61C62B3-ED4B-6957-8916-1B45C6FC082D" vid_target="DDF73358-AE62-C47E-6D35-7443944B37FC">
<hideElementsInCurrentOnly>false</hideElementsInCurrentOnly>
<backgroundColor>-16777216</backgroundColor>
<lineWidth>1</lineWidth>
<points>
<point x="652" y="503"/>
<point x="652" y="415"/>
<point x="453" y="415"/>
</points>
</Connector>
<Connector class="oracle.dbtools.crest.swingui.relational.TVFKRelation" oid="284E8DE0-3EE2-0FA2-6FFF-1C05A5B2B652" otype="FKIndexAssociation" vid_source="6D7F1AC2-9EEC-AA46-0EAA-51EA37291CCA" vid_target="F9FAB16C-E004-F710-A56A-16B4C1EA1F4A">
<hideElementsInCurrentOnly>false</hideElementsInCurrentOnly>
<backgroundColor>-16777216</backgroundColor>
<lineWidth>1</lineWidth>
<points>
<point x="1478" y="518"/>
<point x="2107" y="518"/>
<point x="2107" y="399"/>
</points>
</Connector>
<Connector class="oracle.dbtools.crest.swingui.relational.TVFKRelation" oid="302BE069-52FE-901D-7083-EF1EE2C952B1" otype="FKIndexAssociation" vid_source="E61C62B3-ED4B-6957-8916-1B45C6FC082D" vid_target="4A57AB56-8CB8-9FF1-B6F6-62930E10D589">
<hideElementsInCurrentOnly>false</hideElementsInCurrentOnly>
<backgroundColor>-16777216</backgroundColor>
<lineWidth>1</lineWidth>
<points>
<point x="636" y="637"/>
<point x="475" y="637"/>
</points>
</Connector>
<Connector class="oracle.dbtools.crest.swingui.relational.TVFKRelation" oid="33131824-4D7D-8E38-BFDF-BDF1DB3CA0DF" otype="FKIndexAssociation" vid_source="6D7F1AC2-9EEC-AA46-0EAA-51EA37291CCA" vid_target="7F4C35F9-7094-B775-1E75-5C8B980D02D9">
<hideElementsInCurrentOnly>false</hideElementsInCurrentOnly>
<backgroundColor>-16777216</backgroundColor>
<lineWidth>1</lineWidth>
<points>
<point x="1304" y="486"/>
<point x="1304" y="238"/>
</points>
</Connector>
<Connector class="oracle.dbtools.crest.swingui.relational.TVFKRelation" oid="366FE735-6302-83AE-8960-C4225412E83C" otype="FKIndexAssociation" vid_source="6D7F1AC2-9EEC-AA46-0EAA-51EA37291CCA" vid_target="9AE03005-8EDB-2D3D-98EF-90E44E8E8078">
<hideElementsInCurrentOnly>false</hideElementsInCurrentOnly>
<backgroundColor>-16777216</backgroundColor>
<lineWidth>1</lineWidth>
<points>
<point x="1222" y="683"/>
<point x="1222" y="819"/>
</points>
</Connector>
<Connector class="oracle.dbtools.crest.swingui.relational.TVFKRelation" oid="4A068569-387B-B1B0-4CD7-46DF58AD3081" otype="FKIndexAssociation" vid_source="6D7F1AC2-9EEC-AA46-0EAA-51EA37291CCA" vid_target="D8C0244D-4372-576F-F2A5-13780CB6902D">
<hideElementsInCurrentOnly>false</hideElementsInCurrentOnly>
<backgroundColor>-16777216</backgroundColor>
<lineWidth>1</lineWidth>
<points>
<point x="1399" y="486"/>
<point x="1399" y="292"/>
<point x="1442" y="292"/>
</points>
</Connector>
<Connector class="oracle.dbtools.crest.swingui.relational.TVFKRelation" oid="4DEF1FAF-2EC6-99A8-7E59-EC66B0ACB490" otype="FKIndexAssociation" vid_source="10875E27-7942-D7FD-BC2D-8685C4EFB84E" vid_target="D053F686-7233-6B6D-9028-7E800EDE3FC4">
<hideElementsInCurrentOnly>false</hideElementsInCurrentOnly>
<backgroundColor>-16777216</backgroundColor>
<lineWidth>1</lineWidth>
<points>
<point x="727" y="1049"/>
<point x="727" y="1171"/>
</points>
</Connector>
<Connector class="oracle.dbtools.crest.swingui.relational.TVFKRelation" oid="5C85DB3C-19C1-7E23-E53B-563380F2C258" otype="FKIndexAssociation" vid_source="6D7F1AC2-9EEC-AA46-0EAA-51EA37291CCA" vid_target="E1EA7A8A-44C2-1398-DBC0-9FC899F25D67">
<hideElementsInCurrentOnly>false</hideElementsInCurrentOnly>
<backgroundColor>-16777216</backgroundColor>
<lineWidth>1</lineWidth>
<points>
<point x="1432" y="683"/>
<point x="1432" y="778"/>
</points>
</Connector>
<Connector class="oracle.dbtools.crest.swingui.relational.TVFKRelation" oid="61C4BE95-F3C1-7389-0A39-81AA6583575A" otype="FKIndexAssociation" vid_source="9AE03005-8EDB-2D3D-98EF-90E44E8E8078" vid_target="E61C62B3-ED4B-6957-8916-1B45C6FC082D">
<hideElementsInCurrentOnly>false</hideElementsInCurrentOnly>
<backgroundColor>-16777216</backgroundColor>
<lineWidth>1</lineWidth>
<points>
<point x="1028" y="854"/>
<point x="778" y="854"/>
<point x="778" y="695"/>
</points>
</Connector>
<Connector class="oracle.dbtools.crest.swingui.relational.TVFKRelation" oid="66F30451-6D3F-B371-809B-A2B496CB661E" otype="FKIndexAssociation" vid_source="E61C62B3-ED4B-6957-8916-1B45C6FC082D" vid_target="17D69F52-DC97-ED43-3D14-0DAC1F7EFA80">
<hideElementsInCurrentOnly>false</hideElementsInCurrentOnly>
<backgroundColor>-16777216</backgroundColor>
<lineWidth>1</lineWidth>
<points>
<point x="747" y="503"/>
<point x="747" y="322"/>
</points>
</Connector>
<Connector class="oracle.dbtools.crest.swingui.relational.TVFKRelation" oid="8976DBB2-39A1-C151-3FC0-F4ABD031BA5F" otype="FKIndexAssociation" vid_source="D053F686-7233-6B6D-9028-7E800EDE3FC4" vid_target="ECD4FF18-2A6E-48B2-4BC6-43E7E8F695A8">
<hideElementsInCurrentOnly>false</hideElementsInCurrentOnly>
<backgroundColor>-16777216</backgroundColor>
<lineWidth>1</lineWidth>
<points>
<point x="738" y="1284"/>
<point x="738" y="1399"/>
</points>
</Connector>
<Connector class="oracle.dbtools.crest.swingui.relational.TVFKRelation" oid="8F643967-316B-F31A-57EB-CC6CA019019B" otype="FKIndexAssociation" vid_source="6D7F1AC2-9EEC-AA46-0EAA-51EA37291CCA" vid_target="77A89C16-F31B-95D5-864E-A476AF0E1FC1">
<hideElementsInCurrentOnly>false</hideElementsInCurrentOnly>
<backgroundColor>-16777216</backgroundColor>
<lineWidth>1</lineWidth>
<points>
<point x="1478" y="499"/>
<point x="1827" y="499"/>
<point x="1827" y="411"/>
</points>
</Connector>
<Connector class="oracle.dbtools.crest.swingui.relational.TVFKRelation" oid="98EA73AF-58FB-D35D-B38C-7ABA1C664D4B" otype="FKIndexAssociation" vid_source="E61C62B3-ED4B-6957-8916-1B45C6FC082D" vid_target="10875E27-7942-D7FD-BC2D-8685C4EFB84E">
<hideElementsInCurrentOnly>false</hideElementsInCurrentOnly>
<backgroundColor>-16777216</backgroundColor>
<lineWidth>1</lineWidth>
<points>
<point x="744" y="695"/>
<point x="744" y="889"/>
</points>
</Connector>
<Connector class="oracle.dbtools.crest.swingui.relational.TVFKRelation" oid="BC4DB836-CD40-C934-557A-4C391B6B2B3A" otype="FKIndexAssociation" vid_source="6D7F1AC2-9EEC-AA46-0EAA-51EA37291CCA" vid_target="F90DCE8B-2C27-9257-F516-49C2F3EB688B">
<hideElementsInCurrentOnly>false</hideElementsInCurrentOnly>
<backgroundColor>-16777216</backgroundColor>
<lineWidth>1</lineWidth>
<points>
<point x="1240" y="486"/>
<point x="1240" y="332"/>
<point x="1158" y="332"/>
</points>
</Connector>
<Connector class="oracle.dbtools.crest.swingui.relational.TVFKRelation" oid="BE802E99-83C1-713C-7AC2-F30B43846BC3" otype="FKIndexAssociation" vid_source="E61C62B3-ED4B-6957-8916-1B45C6FC082D" vid_target="6D7F1AC2-9EEC-AA46-0EAA-51EA37291CCA">
<hideElementsInCurrentOnly>false</hideElementsInCurrentOnly>
<backgroundColor>-16777216</backgroundColor>
<lineWidth>1</lineWidth>
<points>
<point x="924" y="593"/>
<point x="1156" y="593"/>
</points>
</Connector>
<Connector class="oracle.dbtools.crest.swingui.relational.TVFKRelation" oid="D650435F-43BD-4426-FFC9-1FA4B9D7D7E8" otype="FKIndexAssociation" vid_source="6D7F1AC2-9EEC-AA46-0EAA-51EA37291CCA" vid_target="E9319264-21B4-086C-C57D-8A3E04F07075">
<hideElementsInCurrentOnly>false</hideElementsInCurrentOnly>
<backgroundColor>-16777216</backgroundColor>
<lineWidth>1</lineWidth>
<points>
<point x="1478" y="609"/>
<point x="1931" y="609"/>
</points>
</Connector>
<Connector class="oracle.dbtools.crest.swingui.relational.TVFKRelation" oid="E9F411ED-66AF-6D3A-E3FE-ED8330B3D5D9" otype="FKIndexAssociation" vid_source="6D7F1AC2-9EEC-AA46-0EAA-51EA37291CCA" vid_target="A434CD4D-D16D-93C9-9F74-BD060AEE9DA1">
<hideElementsInCurrentOnly>false</hideElementsInCurrentOnly>
<backgroundColor>-16777216</backgroundColor>
<lineWidth>1</lineWidth>
<points>
<point x="1345" y="683"/>
<point x="1345" y="1089"/>
</points>
</Connector>
</connectors>
</Diagram>
